motoo/__init__.py
motoo/wit_util.py
motoo-1.1.95.dist-info/METADATA
motoo-1.1.95.dist-info/WHEEL
motoo-1.1.95.dist-info/top_level.txt
motoo-1.1.95.dist-info/RECORD
