Metadata-Version: 2.1
Name: motoo
Version: 1.1.95
Summary: motoo utils
Home-page: UNKNOWN
Author: ffolio
Author-email: david@ffolio.co.kr
License: UNKNOWN
Keywords: pypi deploy
Platform: UNKNOWN
Classifier: Programming Language :: Python :: 3
Classifier: Programming Language :: Python :: 3.2
Classifier: Programming Language :: Python :: 3.3
Classifier: Programming Language :: Python :: 3.4
Classifier: Programming Language :: Python :: 3.5
Classifier: Programming Language :: Python :: 3.6
Classifier: Programming Language :: Python :: 3.7
Requires-Python: >=3
Requires-Dist: boto3
Requires-Dist: numpy
Requires-Dist: pandas
Requires-Dist: requests
Requires-Dist: scipy
